{
  "task_id": "twitter_quick_win_20260210_202841",
  "task_type": "twitter_action",
  "trigger": "quick_win",
  "priority": "medium",
  "created_at": "2026-02-10T20:28:41.984281",
  "content": {
    "win_description": "Instagram_Integration_Complete",
    "context": "\ud83c\udf89 instagram integration complete! \n\nafter hours of setup challenges, we've successfully connected @muhammad.ahmed.3914 to the personal ai employee system.\n\nkey achievements:\n\u2705 converted to business account\n\u2705 connected to my test page\n\u2705 added as instagram tester\n\u2705 generated access token\n\u2705 api access verified\n\nthis milestone post is automatically generated by ai to celebrate the completion of instagram integration for the gold tier features.\n\n#personalai #instagramapi #automation #goldtier #milest"
  },
  "instructions": "Review obsidian_vault/agent_skills/twitter_skills.md for posting guidelines.\n\nTask: Share quick win on Twitter\n\nWin: Instagram_Integration_Complete\nContext: \ud83c\udf89 instagram integration complete! \n\nafter hours of setup challenges, we've successfully connected @muhammad.ahmed.3914 to the personal ai employee system.\n\nkey achievements:\n\u2705 converted to business account\n\u2705 connected to my test page\n\u2705 added as instagram tester\n\u2705 generated access token\n\u2705 api access verified\n\nthis milestone post is automatically generated by ai to celebrate the completion of instagram integration for the gold tier features.\n\n#personalai #instagramapi #automation #goldtier #milest\n\nAction Steps:\n1. Identify core achievement (completed project, client win, milestone)\n2. Write celebratory but professional tweet\n3. Use 1 emoji opener (\ud83c\udf89 \u2705 \ud83d\ude80)\n4. Keep under 250 characters for easy RT\n5. Tag relevant people/companies if appropriate (max 2 tags)\n6. Add 2-3 hashtags\n7. Auto-approve if non-sensitive\n8. Post and engage with responses\n\nTweet Tone:\n- Excited but not boastful\n- Specific outcome, not vague \"great work\"\n- Give credit to team/client where appropriate\n- Invite engagement (\"What's your approach?\")\n"
}